gpcc/__init__.py
gpcc/__main__.py
gpcc/_cli.py
gpcc/_crawlers.py
gpcc/_schemas.py
gpcc/py.typed
gpcc-1.1.0.dist-info/LICENSE
gpcc-1.1.0.dist-info/WHEEL
gpcc-1.1.0.dist-info/METADATA
gpcc-1.1.0.dist-info/RECORD
