Metadata-Version: 2.1
Name: gpcc
Version: 1.1.0
Summary: Fetch data from https://gpc-browser.gs1.org/.
Author-email: Gram <git@orsinium.dev>
Requires-Python: >=3.8
Classifier: Development Status :: 5 - Production/Stable
Classifier: Intended Audience :: Developers
Classifier: License :: OSI Approved :: MIT License
Classifier: Programming Language :: Python
Classifier: Typing :: Typed
Requires-Dist: aiohttp
Project-URL: Source, https://github.com/orsinium-labs/gpcc
